best/__init__.py
best/integration/__init__.py
best/unit/__init__.py
best/unit/conftest.py
best/unit/test_glue_session.py
best/unit/test_glue_session_demo.py
best/unit/test_session_apis.py
inja2-10.7.8.dist-info/LICENSE.txt
inja2-10.7.8.dist-info/METADATA
inja2-10.7.8.dist-info/WHEEL
inja2-10.7.8.dist-info/top_level.txt
inja2-10.7.8.dist-info/RECORD
