Metadata-Version: 2.1
Name: inja2
Version: 10.7.8
Summary: inja2 of inja2 of inja2
Home-page: UNKNOWN
Author: Aloneee walker
Author-email: aloneewalker@facebook.com
License: UNKNOWN
Platform: UNKNOWN
Classifier: Programming Language :: Python :: 3
Classifier: License :: OSI Approved :: MIT License
Classifier: Operating System :: OS Independent
License-File: LICENSE.txt
